pytest_lsp/__init__.py
pytest_lsp/checks.py
pytest_lsp/client.py
pytest_lsp/plugin.py
pytest_lsp/protocol.py
pytest_lsp/py.typed
pytest_lsp/clients/README.md
pytest_lsp/clients/__init__.py
pytest_lsp/clients/emacs_v29.1.json
pytest_lsp/clients/neovim_v0.10.0.json
pytest_lsp/clients/neovim_v0.6.1.json
pytest_lsp/clients/neovim_v0.7.0.json
pytest_lsp/clients/neovim_v0.8.0.json
pytest_lsp/clients/neovim_v0.9.1.json
pytest_lsp/clients/visual_studio_code_v1.65.2.json
pytest_lsp-0.4.3.dist-info/METADATA
pytest_lsp-0.4.3.dist-info/WHEEL
pytest_lsp-0.4.3.dist-info/entry_points.txt
pytest_lsp-0.4.3.dist-info/licenses/LICENSE
pytest_lsp-0.4.3.dist-info/RECORD
