Metadata-Version: 2.3
Name: pytest-lsp
Version: 0.4.3
Summary: A pytest plugin for end-to-end testing of language servers
Project-URL: Bug Tracker, https://github.com/swyddfa/lsp-devtools/issues
Project-URL: Documentation, https://lsp-devtools.readthedocs.io/en/latest/
Project-URL: Source Code, https://github.com/swyddfa/lsp-devtools
Author-email: Alex Carney <alcarneyme@gmail.com>
License: MIT
License-File: LICENSE
Classifier: Development Status :: 3 - Alpha
Classifier: Framework :: Pytest
Classifier: License :: OSI Approved :: MIT License
Classifier: Programming Language :: Python
Classifier: Programming Language :: Python :: 3
Classifier: Programming Language :: Python :: 3 :: Only
Classifier: Programming Language :: Python :: 3.8
Classifier: Programming Language :: Python :: 3.9
Classifier: Programming Language :: Python :: 3.10
Classifier: Programming Language :: Python :: 3.11
Classifier: Programming Language :: Python :: 3.12
Requires-Python: >=3.8
Requires-Dist: importlib-resources; python_version < '3.9'
Requires-Dist: packaging
Requires-Dist: pygls>=1.1.0
Requires-Dist: pytest
Requires-Dist: pytest-asyncio>=0.23
